explainpolysvm/__init__.py
explainpolysvm/expsvm.py
explainpolysvm/plot/__init__.py
explainpolysvm/plot/_bar.py
explainpolysvm/plot/_waterfall.py
explainpolysvm-1.1.3.dist-info/METADATA
explainpolysvm-1.1.3.dist-info/WHEEL
explainpolysvm-1.1.3.dist-info/licenses/LICENSE
explainpolysvm-1.1.3.dist-info/RECORD
