Metadata-Version: 2.4
Name: explainpolysvm
Version: 1.1.3
Summary: Module for Global and Local explanations and feature selection for Support Vector Machines trained with polynomial kernels.
Project-URL: Repository, https://github.com/rikardvinge/explainpolysvm.git
Project-URL: Issues, https://github.com/rikardvinge/explainpolysvm/issues
Author-email: Rikard Vinge <research@rikardvinge.se>
License: BSD-3-Clause
License-File: LICENSE
Keywords: feature importance,feature selection,interaction importance,polynomial kernel,support vector machine,svm,xai
Classifier: Development Status :: 5 - Production/Stable
Classifier: Intended Audience :: Developers
Classifier: Intended Audience :: Education
Classifier: Intended Audience :: Science/Research
Classifier: Programming Language :: Python :: 3
Classifier: Programming Language :: Python :: 3.8
Classifier: Programming Language :: Python :: 3.9
Classifier: Programming Language :: Python :: 3.10
Classifier: Programming Language :: Python :: 3.11
Classifier: Programming Language :: Python :: 3.12
Classifier: Programming Language :: Python :: 3.13
Classifier: Topic :: Scientific/Engineering :: Artificial Intelligence
Requires-Python: >=3.8
Requires-Dist: matplotlib
Requires-Dist: numpy>=1.24.4
Requires-Dist: scikit-learn>=1.0.2
Provides-Extra: dev
Requires-Dist: pytest>=7.0; extra == 'dev'
